{
  "1001": [
    {
      "name": "General",
      "specifications": [
        {
          "key": "Call Features",
          "value": "Loudspeaker"
        },
        {
          "key": "Touch Screen",
          "value": "Yes"
        },
        {
          "key": "SIM Type",
          "value": "GSM, Single Sim"
        },
        {
          "key": "Sim Size",
          "value": "Nano Sim"
        },
        {
          "key": "Video Calling",
          "value": "Yes"
        }
      ]
    },
    {
      "name": "Platform",
      "specifications": [
        {
          "key": "Processor",
          "value": "1.4 GHz + A8 Chip with 64 bit architecture"
        },
        {
          "key": "OS",
          "value": "iOS 9"
        }
      ]
    },
    {
      "name": "Display",
      "specifications": [
        {
          "key": "Screen Size",
          "value": "4.7 inches"
        },
        {
          "key": "Screen Type",
          "value": "FullHD"
        },
        {
          "key": "Screen Resolution",
          "value": "1334x750 Pixels"
        }
      ]
    },
    {
      "name": "Memory & Storage",
      "specifications": [
        {
          "key": "RAM",
          "value": "1GB"
        },
        {
          "key": "Internal Storage",
          "value": "16GB"
        }
      ]
    },
    {
      "name": "Camera",
      "specifications": [
        {
          "key": "Primary Camera",
          "value": "Yes, 8MP"
        },
        {
          "key": "Secondary Camera",
          "value": "Yes, 1.2MP"
        }
      ]
    },
    {
      "name": "Dimensions",
      "specifications": [
        {
          "key": "Size",
          "value": "67x138.1x6.9mm"
        },
        {
          "key": "Weight",
          "value": "129 gm"
        }
      ]
    }
  ],
  "1002": [
    {
      "name": "General",
      "specifications": [
        {
          "key": "Call Features",
          "value": "Loudspeaker"
        },
        {
          "key": "Touch Screen",
          "value": "Yes"
        },
        {
          "key": "SIM Type",
          "value": "GSM, Single Sim"
        },
        {
          "key": "Sim Size",
          "value": "Nano Sim"
        },
        {
          "key": "Video Calling",
          "value": "Yes"
        }
      ]
    },
    {
      "name": "Platform",
      "specifications": [
        {
          "key": "Processor",
          "value": "1.4 GHz + A8 Chip with 64 bit architecture"
        },
        {
          "key": "OS",
          "value": "iOS v8"
        }
      ]
    },
    {
      "name": "Display",
      "specifications": [
        {
          "key": "Screen Size",
          "value": "4.7 inches"
        },
        {
          "key": "Screen Type",
          "value": "IPS display"
        },
        {
          "key": "Screen Resolution",
          "value": "1334x750 Pixels"
        }
      ]
    },
    {
      "name": "Memory & Storage",
      "specifications": [
        {
          "key": "RAM",
          "value": "1GB"
        },
        {
          "key": "Internal Storage",
          "value": "64GB"
        }
      ]
    },
    {
      "name": "Camera",
      "specifications": [
        {
          "key": "Primary Camera",
          "value": "Yes, 8MP"
        },
        {
          "key": "Secondary Camera",
          "value": "Yes, 1.2MP"
        }
      ]
    },
    {
      "name": "Dimensions",
      "specifications": [
        {
          "key": "Size",
          "value": "67x138.1x6.9mm"
        },
        {
          "key": "Weight",
          "value": "129 gm"
        }
      ]
    }
  ],
  "1003": [
    {
      "name": "General",
      "specifications": [
        {
          "key": "Call Features",
          "value": "Loudspeaker"
        },
        {
          "key": "Touch Screen",
          "value": "Yes"
        },
        {
          "key": "SIM Type",
          "value": "GSM, Single Sim"
        },
        {
          "key": "Sim Size",
          "value": "Nano Sim"
        },
        {
          "key": "Video Calling",
          "value": "Yes"
        }
      ]
    },
    {
      "name": "Platform",
      "specifications": [
        {
          "key": "Processor",
          "value": "1.4 GHz + A8 Chip with 64 bit architecture"
        },
        {
          "key": "OS",
          "value": "iOS 8"
        }
      ]
    },
    {
      "name": "Display",
      "specifications": [
        {
          "key": "Screen Size",
          "value": "4.7 inches"
        },
        {
          "key": "Screen Type",
          "value": "FullHD"
        },
        {
          "key": "Screen Resolution",
          "value": "1334x750 Pixels"
        }
      ]
    },
    {
      "name": "Memory & Storage",
      "specifications": [
        {
          "key": "RAM",
          "value": "1GB"
        },
        {
          "key": "Internal Storage",
          "value": "128GB"
        }
      ]
    },
    {
      "name": "Camera",
      "specifications": [
        {
          "key": "Primary Camera",
          "value": "Yes, 8MP"
        },
        {
          "key": "Secondary Camera",
          "value": "Yes, 1.2MP"
        }
      ]
    },
    {
      "name": "Dimensions",
      "specifications": [
        {
          "key": "Size",
          "value": "67x138.1x6.9mm"
        },
        {
          "key": "Weight",
          "value": "129 gm"
        }
      ]
    }
  ],
  "1004": [
    {
      "name": "General",
      "specifications": [
        {
          "key": "Call Features",
          "value": "Loudspeaker"
        },
        {
          "key": "Touch Screen",
          "value": "Yes"
        },
        {
          "key": "SIM Type",
          "value": "GSM, Single Sim"
        },
        {
          "key": "Sim Size",
          "value": "Nano Sim"
        },
        {
          "key": "Video Calling",
          "value": "Yes"
        }
      ]
    },
    {
      "name": "Platform",
      "specifications": [
        {
          "key": "Processor",
          "value": "1.4 GHz + A8 Chip with 64 bit architecture"
        },
        {
          "key": "OS",
          "value": "iOS 8"
        }
      ]
    },
    {
      "name": "Display",
      "specifications": [
        {
          "key": "Screen Size",
          "value": "5.5 inches"
        },
        {
          "key": "Screen Type",
          "value": "FullHD"
        },
        {
          "key": "Screen Resolution",
          "value": "1334x750 Pixels"
        }
      ]
    },
    {
      "name": "Memory & Storage",
      "specifications": [
        {
          "key": "RAM",
          "value": "1GB"
        },
        {
          "key": "Internal Storage",
          "value": "16GB"
        }
      ]
    },
    {
      "name": "Camera",
      "specifications": [
        {
          "key": "Primary Camera",
          "value": "Yes, 8MP"
        },
        {
          "key": "Secondary Camera",
          "value": "Yes, 1.2MP"
        }
      ]
    },
    {
      "name": "Dimensions",
      "specifications": [
        {
          "key": "Size",
          "value": "67x138.1x6.9mm"
        },
        {
          "key": "Weight",
          "value": "129 gm"
        }
      ]
    }
  ],
  "1005": [
    {
      "name": "General",
      "specifications": [
        {
          "key": "Call Features",
          "value": "Loudspeaker"
        },
        {
          "key": "Touch Screen",
          "value": "Yes"
        },
        {
          "key": "SIM Type",
          "value": "GSM, Single Sim"
        },
        {
          "key": "Sim Size",
          "value": "Nano Sim"
        },
        {
          "key": "Video Calling",
          "value": "Yes"
        }
      ]
    },
    {
      "name": "Platform",
      "specifications": [
        {
          "key": "Processor",
          "value": "1.4 GHz + A8 Chip with 64 bit architecture"
        },
        {
          "key": "OS",
          "value": "iOS 8"
        }
      ]
    },
    {
      "name": "Display",
      "specifications": [
        {
          "key": "Screen Size",
          "value": "5.5 inches"
        },
        {
          "key": "Screen Type",
          "value": "FullHD"
        },
        {
          "key": "Screen Resolution",
          "value": "1334x750 Pixels"
        }
      ]
    },
    {
      "name": "Memory & Storage",
      "specifications": [
        {
          "key": "RAM",
          "value": "1GB"
        },
        {
          "key": "Internal Storage",
          "value": "64GB"
        }
      ]
    },
    {
      "name": "Camera",
      "specifications": [
        {
          "key": "Primary Camera",
          "value": "Yes, 8MP"
        },
        {
          "key": "Secondary Camera",
          "value": "Yes, 1.2MP"
        }
      ]
    },
    {
      "name": "Dimensions",
      "specifications": [
        {
          "key": "Size",
          "value": "67x138.1x6.9mm"
        },
        {
          "key": "Weight",
          "value": "129 gm"
        }
      ]
    }
  ],
  "1006": [
    {
      "name": "General",
      "specifications": [
        {
          "key": "Call Features",
          "value": "Loudspeaker"
        },
        {
          "key": "Touch Screen",
          "value": "Yes"
        },
        {
          "key": "SIM Type",
          "value": "GSM, Single Sim"
        },
        {
          "key": "Sim Size",
          "value": "Nano Sim"
        },
        {
          "key": "Video Calling",
          "value": "Yes"
        }
      ]
    },
    {
      "name": "Platform",
      "specifications": [
        {
          "key": "Processor",
          "value": "A6 chip"
        },
        {
          "key": "OS",
          "value": "iOS 7"
        }
      ]
    },
    {
      "name": "Display",
      "specifications": [
        {
          "key": "Screen Size",
          "value": "4 inches"
        },
        {
          "key": "Screen Type",
          "value": "Retina display"
        },
        {
          "key": "Screen Resolution",
          "value": "1136x640 Pixels"
        }
      ]
    },
    {
      "name": "Memory & Storage",
      "specifications": [
        {
          "key": "RAM",
          "value": "1GB"
        },
        {
          "key": "Internal Storage",
          "value": "16GB"
        }
      ]
    },
    {
      "name": "Camera",
      "specifications": [
        {
          "key": "Primary Camera",
          "value": "Yes, 8MP"
        },
        {
          "key": "Secondary Camera",
          "value": "Yes, 1.2MP"
        }
      ]
    },
    {
      "name": "Dimensions",
      "specifications": [
        {
          "key": "Size",
          "value": "59.2x124.4x8.97 mm"
        },
        {
          "key": "Weight",
          "value": "132 gm"
        }
      ]
    }
  ],
  "1007": [
    {
      "name": "General",
      "specifications": [
        {
          "key": "Call Features",
          "value": "Loudspeaker"
        },
        {
          "key": "Touch Screen",
          "value": "Yes"
        },
        {
          "key": "SIM Type",
          "value": "GSM, Single Sim"
        },
        {
          "key": "Sim Size",
          "value": "Nano Sim"
        },
        {
          "key": "Video Calling",
          "value": "Yes"
        }
      ]
    },
    {
      "name": "Platform",
      "specifications": [
        {
          "key": "Processor",
          "value": "A6 chip"
        },
        {
          "key": "OS",
          "value": "iOS 7"
        }
      ]
    },
    {
      "name": "Display",
      "specifications": [
        {
          "key": "Screen Size",
          "value": "4 inches"
        },
        {
          "key": "Screen Type",
          "value": "Retina display"
        },
        {
          "key": "Screen Resolution",
          "value": "1136x640 Pixels"
        }
      ]
    },
    {
      "name": "Memory & Storage",
      "specifications": [
        {
          "key": "RAM",
          "value": "1GB"
        },
        {
          "key": "Internal Storage",
          "value": "16GB"
        }
      ]
    },
    {
      "name": "Camera",
      "specifications": [
        {
          "key": "Primary Camera",
          "value": "Yes, 8MP"
        },
        {
          "key": "Secondary Camera",
          "value": "Yes, 1.2MP"
        }
      ]
    },
    {
      "name": "Dimensions",
      "specifications": [
        {
          "key": "Size",
          "value": "59.2x124.4x8.97 mm"
        },
        {
          "key": "Weight",
          "value": "132 gm"
        }
      ]
    }
  ],
  "1008": [
    {
      "name": "General",
      "specifications": [
        {
          "key": "Call Features",
          "value": "Loudspeaker"
        },
        {
          "key": "Touch Screen",
          "value": "Yes"
        },
        {
          "key": "SIM Type",
          "value": "GSM, Single Sim"
        },
        {
          "key": "Sim Size",
          "value": "Nano Sim"
        },
        {
          "key": "Video Calling",
          "value": "Yes"
        }
      ]
    },
    {
      "name": "Platform",
      "specifications": [
        {
          "key": "Processor",
          "value": "A7 chip"
        },
        {
          "key": "OS",
          "value": "iOS 6"
        }
      ]
    },
    {
      "name": "Display",
      "specifications": [
        {
          "key": "Screen Size",
          "value": "4 inches"
        },
        {
          "key": "Screen Type",
          "value": "Retina display"
        },
        {
          "key": "Screen Resolution",
          "value": "1136 x 640 Pixels"
        }
      ]
    },
    {
      "name": "Memory & Storage",
      "specifications": [
        {
          "key": "RAM",
          "value": "1GB"
        },
        {
          "key": "Internal Storage",
          "value": "16GB"
        }
      ]
    },
    {
      "name": "Camera",
      "specifications": [
        {
          "key": "Primary Camera",
          "value": "Yes, 8MP"
        },
        {
          "key": "Secondary Camera",
          "value": "Yes, 1.2MP"
        }
      ]
    },
    {
      "name": "Dimensions",
      "specifications": [
        {
          "key": "Size",
          "value": "58.6x123.8x7.6 mm"
        },
        {
          "key": "Weight",
          "value": "112 gm"
        }
      ]
    }
  ],
  "1009": [
    {
      "name": "General",
      "specifications": [
        {
          "key": "Call Features",
          "value": "Loudspeaker"
        },
        {
          "key": "Touch Screen",
          "value": "Yes"
        },
        {
          "key": "SIM Type",
          "value": "GSM, Single Sim"
        },
        {
          "key": "Sim Size",
          "value": "Nano Sim"
        },
        {
          "key": "Video Calling",
          "value": "Yes"
        }
      ]
    },
    {
      "name": "Platform",
      "specifications": [
        {
          "key": "Processor",
          "value": "A6 chip"
        },
        {
          "key": "OS",
          "value": "iOS 6"
        }
      ]
    },
    {
      "name": "Display",
      "specifications": [
        {
          "key": "Screen Size",
          "value": "4 inches"
        },
        {
          "key": "Screen Type",
          "value": "IPS display"
        },
        {
          "key": "Screen Resolution",
          "value": "1136x640 Pixels"
        }
      ]
    },
    {
      "name": "Memory & Storage",
      "specifications": [
        {
          "key": "RAM",
          "value": "1GB"
        },
        {
          "key": "Internal Storage",
          "value": "32GB"
        }
      ]
    },
    {
      "name": "Camera",
      "specifications": [
        {
          "key": "Primary Camera",
          "value": "Yes, 5MP"
        },
        {
          "key": "Secondary Camera",
          "value": "Yes, 1.2MP"
        }
      ]
    },
    {
      "name": "Dimensions",
      "specifications": [
        {
          "key": "Size",
          "value": "67x138.1x6.9mm"
        },
        {
          "key": "Weight",
          "value": "112 gm"
        }
      ]
    }
  ],
  "1010": [
    {
      "name": "General",
      "specifications": [
        {
          "key": "Call Features",
          "value": "Loudspeaker"
        },
        {
          "key": "Touch Screen",
          "value": "Yes"
        },
        {
          "key": "SIM Type",
          "value": "GSM, Single Sim"
        },
        {
          "key": "Sim Size",
          "value": "Nano Sim"
        },
        {
          "key": "Video Calling",
          "value": "Yes"
        }
      ]
    },
    {
      "name": "Platform",
      "specifications": [
        {
          "key": "Processor",
          "value": "A6 chip"
        },
        {
          "key": "OS",
          "value": "iOS 6"
        }
      ]
    },
    {
      "name": "Display",
      "specifications": [
        {
          "key": "Screen Size",
          "value": "3.5 inches"
        },
        {
          "key": "Screen Type",
          "value": "IPS display"
        },
        {
          "key": "Screen Resolution",
          "value": "1134x640 Pixels"
        }
      ]
    },
    {
      "name": "Memory & Storage",
      "specifications": [
        {
          "key": "RAM",
          "value": "1GB"
        },
        {
          "key": "Internal Storage",
          "value": "8GB"
        }
      ]
    },
    {
      "name": "Camera",
      "specifications": [
        {
          "key": "Primary Camera",
          "value": "Yes, 8MP"
        },
        {
          "key": "Secondary Camera",
          "value": "Yes, 1.2MP"
        }
      ]
    },
    {
      "name": "Dimensions",
      "specifications": [
        {
          "key": "Size",
          "value": "67x138.1x6.9mm"
        },
        {
          "key": "Weight",
          "value": "100 gm"
        }
      ]
    }
  ],
  "1011": [
    {
      "name": "General",
      "specifications": [
        {
          "key": "Call Features",
          "value": "Loudspeaker"
        },
        {
          "key": "Touch Screen",
          "value": "Yes"
        },
        {
          "key": "SIM Type",
          "value": "GSM + LTE, Dual Sim"
        },
        {
          "key": "Sim Size",
          "value": "Micro Sim"
        },
        {
          "key": "Video Calling",
          "value": "Yes"
        }
      ]
    },
    {
      "name": "Platform",
      "specifications": [
        {
          "key": "Processor",
          "value": "1.4 GHz + Qualcomm Snapdragon 410 MSM8916, Quad Core"
        },
        {
          "key": "OS",
          "value": "Android v5.1.1 (Lollipop)"
        }
      ]
    },
    {
      "name": "Display",
      "specifications": [
        {
          "key": "Screen Size",
          "value": "5 inches"
        },
        {
          "key": "Screen Type",
          "value": "FullHD"
        },
        {
          "key": "Screen Resolution",
          "value": "1280 x 720 Pixels"
        }
      ]
    },
    {
      "name": "Memory & Storage",
      "specifications": [
        {
          "key": "RAM",
          "value": "2GB"
        },
        {
          "key": "Internal Storage",
          "value": "16GB"
        }
      ]
    },
    {
      "name": "Camera",
      "specifications": [
        {
          "key": "Primary Camera",
          "value": "Yes, 13MP"
        },
        {
          "key": "Secondary Camera",
          "value": "Yes, 5MP"
        }
      ]
    },
    {
      "name": "Dimensions",
      "specifications": [
        {
          "key": "Size",
          "value": "72.4x142.1 mm"
        },
        {
          "key": "Weight",
          "value": "155 gm"
        }
      ]
    }
  ],
  "1012": [
    {
      "name": "General",
      "specifications": [
        {
          "key": "Call Features",
          "value": "Loudspeaker"
        },
        {
          "key": "Touch Screen",
          "value": "Yes"
        },
        {
          "key": "SIM Type",
          "value": "GSM + GSM, Dual Sim"
        },
        {
          "key": "Sim Size",
          "value": "Micro Sim"
        },
        {
          "key": "Video Calling",
          "value": "Yes"
        }
      ]
    },
    {
      "name": "Platform",
      "specifications": [
        {
          "key": "Processor",
          "value": "2.5 GHz + Qualcomm Snapdragon 801 MSM8974-AC, Quad Core"
        },
        {
          "key": "OS",
          "value": "Android v4.4.4 (KitKat), Upgradable to v5.0 (Lollipop)(OTA Upgrade)"
        }
      ]
    },
    {
      "name": "Display",
      "specifications": [
        {
          "key": "Screen Size",
          "value": "5.2 inches"
        },
        {
          "key": "Screen Type",
          "value": "FullHD"
        },
        {
          "key": "Screen Resolution",
          "value": "1920 x 1080 Pixels"
        }
      ]
    },
    {
      "name": "Memory & Storage",
      "specifications": [
        {
          "key": "RAM",
          "value": "2GB"
        },
        {
          "key": "Internal Storage",
          "value": "16GB"
        }
      ]
    },
    {
      "name": "Camera",
      "specifications": [
        {
          "key": "Primary Camera",
          "value": "Yes, 13MP"
        },
        {
          "key": "Secondary Camera",
          "value": "Yes, 2MP"
        }
      ]
    },
    {
      "name": "Dimensions",
      "specifications": [
        {
          "key": "Size",
          "value": "67x138.1x6.9mm"
        },
        {
          "key": "Weight",
          "value": "144 gm"
        }
      ]
    }
  ],
  "1013": [
    {
      "name": "General",
      "specifications": [
        {
          "key": "Call Features",
          "value": "Loudspeaker"
        },
        {
          "key": "Touch Screen",
          "value": "Yes"
        },
        {
          "key": "SIM Type",
          "value": "LTE + LTE, dual Sim"
        },
        {
          "key": "Sim Size",
          "value": "Nano Sim"
        },
        {
          "key": "Video Calling",
          "value": "Yes"
        }
      ]
    },
    {
      "name": "Platform",
      "specifications": [
        {
          "key": "Processor",
          "value": "1.7 GHz + Qualcomm Snapdragon 615, Octa Core"
        },
        {
          "key": "OS",
          "value": "v5.0 (Lollipop)"
        }
      ]
    },
    {
      "name": "Display",
      "specifications": [
        {
          "key": "Screen Size",
          "value": "5.5 inches"
        },
        {
          "key": "Screen Type",
          "value": "FullHD"
        },
        {
          "key": "Screen Resolution",
          "value": "1920 x 1080 Pixels"
        }
      ]
    },
    {
      "name": "Memory & Storage",
      "specifications": [
        {
          "key": "RAM",
          "value": "2GB"
        },
        {
          "key": "Internal Storage",
          "value": "16GB"
        }
      ]
    },
    {
      "name": "Camera",
      "specifications": [
        {
          "key": "Primary Camera",
          "value": "Yes, 21MP"
        },
        {
          "key": "Secondary Camera",
          "value": "Yes, 5MP"
        }
      ]
    },
    {
      "name": "Dimensions",
      "specifications": [
        {
          "key": "Size",
          "value": "67x138.1x6.9mm"
        },
        {
          "key": "Weight",
          "value": "169 gm"
        }
      ]
    }
  ],
  "1014": [
    {
      "name": "General",
      "specifications": [
        {
          "key": "Call Features",
          "value": "Loudspeaker"
        },
        {
          "key": "Touch Screen",
          "value": "Yes"
        },
        {
          "key": "SIM Type",
          "value": "LTE + LTE, dual Sim"
        },
        {
          "key": "Sim Size",
          "value": "Nano Sim"
        },
        {
          "key": "Video Calling",
          "value": "Yes"
        }
      ]
    },
    {
      "name": "Platform",
      "specifications": [
        {
          "key": "Processor",
          "value": "1.7 GHz + Qualcomm Snapdragon 615, Octa Core"
        },
        {
          "key": "OS",
          "value": "v5.0 (Lollipop)"
        }
      ]
    },
    {
      "name": "Display",
      "specifications": [
        {
          "key": "Screen Size",
          "value": "5.5 inches"
        },
        {
          "key": "Screen Type",
          "value": "FullHD"
        },
        {
          "key": "Screen Resolution",
          "value": "1920 x 1080 Pixels"
        }
      ]
    },
    {
      "name": "Memory & Storage",
      "specifications": [
        {
          "key": "RAM",
          "value": "2GB"
        },
        {
          "key": "Internal Storage",
          "value": "32GB"
        }
      ]
    },
    {
      "name": "Camera",
      "specifications": [
        {
          "key": "Primary Camera",
          "value": "Yes, 21MP"
        },
        {
          "key": "Secondary Camera",
          "value": "Yes, 5MP"
        }
      ]
    },
    {
      "name": "Dimensions",
      "specifications": [
        {
          "key": "Size",
          "value": "67x138.1x6.9mm"
        },
        {
          "key": "Weight",
          "value": "169 gm"
        }
      ]
    }
  ],
  "1015": [
    {
      "name": "General",
      "specifications": [
        {
          "key": "Call Features",
          "value": "Loudspeaker"
        },
        {
          "key": "Touch Screen",
          "value": "Yes"
        },
        {
          "key": "SIM Type",
          "value": "LTE + LTE, dual Sim"
        },
        {
          "key": "Sim Size",
          "value": "Nano Sim"
        },
        {
          "key": "Video Calling",
          "value": "Yes"
        }
      ]
    },
    {
      "name": "Platform",
      "specifications": [
        {
          "key": "Processor",
          "value": "1.7 GHz + Qualcomm Snapdragon 615, Octa Core"
        },
        {
          "key": "OS",
          "value": "v5.0 (Lollipop)"
        }
      ]
    },
    {
      "name": "Display",
      "specifications": [
        {
          "key": "Screen Size",
          "value": "5.2 inches"
        },
        {
          "key": "Screen Type",
          "value": "AMOLED"
        },
        {
          "key": "Screen Resolution",
          "value": "2560 X 1440 Pixels"
        }
      ]
    },
    {
      "name": "Memory & Storage",
      "specifications": [
        {
          "key": "RAM",
          "value": "3GB"
        },
        {
          "key": "Internal Storage",
          "value": "64GB"
        }
      ]
    },
    {
      "name": "Camera",
      "specifications": [
        {
          "key": "Primary Camera",
          "value": "Yes, 21MP"
        },
        {
          "key": "Secondary Camera",
          "value": "Yes, 2MP"
        }
      ]
    },
    {
      "name": "Dimensions",
      "specifications": [
        {
          "key": "Size",
          "value": "67x138.1x6.9mm"
        },
        {
          "key": "Weight",
          "value": "176 gm"
        }
      ]
    }
  ],
  "1016": [
    {
      "name": "General",
      "specifications": [
        {
          "key": "Call Features",
          "value": "Loudspeaker"
        },
        {
          "key": "Touch Screen",
          "value": "Yes"
        },
        {
          "key": "SIM Type",
          "value": "LTE + LTE, dual Sim"
        },
        {
          "key": "Sim Size",
          "value": "Micro Sim"
        },
        {
          "key": "Video Calling",
          "value": "Yes"
        }
      ]
    },
    {
      "name": "Platform",
      "specifications": [
        {
          "key": "Processor",
          "value": "1.7 GHz + 2nd-gen Snapdragon 615 64-bit octa-core, Octa Core"
        },
        {
          "key": "OS",
          "value": "v5.0 (Lollipop)"
        }
      ]
    },
    {
      "name": "Display",
      "specifications": [
        {
          "key": "Screen Size",
          "value": "5 inches"
        },
        {
          "key": "Screen Type",
          "value": "FullHD"
        },
        {
          "key": "Screen Resolution",
          "value": "1920 x 1080 Pixels"
        }
      ]
    },
    {
      "name": "Memory & Storage",
      "specifications": [
        {
          "key": "RAM",
          "value": "2GB"
        },
        {
          "key": "Internal Storage",
          "value": "16GB"
        }
      ]
    },
    {
      "name": "Camera",
      "specifications": [
        {
          "key": "Primary Camera",
          "value": "Yes, 13MP"
        },
        {
          "key": "Secondary Camera",
          "value": "Yes, 5MP"
        }
      ]
    },
    {
      "name": "Dimensions",
      "specifications": [
        {
          "key": "Size",
          "value": "67x138.1x6.9mm"
        },
        {
          "key": "Weight",
          "value": "130 gm"
        }
      ]
    }
  ],
  "1017": [
    {
      "name": "General",
      "specifications": [
        {
          "key": "Call Features",
          "value": "Loudspeaker"
        },
        {
          "key": "Touch Screen",
          "value": "Yes"
        },
        {
          "key": "SIM Type",
          "value": "GSM, Single Sim"
        },
        {
          "key": "Sim Size",
          "value": "Micro Sim"
        },
        {
          "key": "Video Calling",
          "value": "Yes"
        }
      ]
    },
    {
      "name": "Platform",
      "specifications": [
        {
          "key": "Processor",
          "value": "2.5 GHz + Qualcomm MSM8274AC Snapdragon 801 Krait 400, Quad Core"
        },
        {
          "key": "OS",
          "value": "Android v4.4.4 (KitKat)"
        }
      ]
    },
    {
      "name": "Display",
      "specifications": [
        {
          "key": "Screen Size",
          "value": "5 inches"
        },
        {
          "key": "Screen Type",
          "value": "FullHD"
        },
        {
          "key": "Screen Resolution",
          "value": "1920 x 1080 Pixels"
        }
      ]
    },
    {
      "name": "Memory & Storage",
      "specifications": [
        {
          "key": "RAM",
          "value": "3GB"
        },
        {
          "key": "Internal Storage",
          "value": "16GB"
        }
      ]
    },
    {
      "name": "Camera",
      "specifications": [
        {
          "key": "Primary Camera",
          "value": "Yes, 13MP"
        },
        {
          "key": "Secondary Camera",
          "value": "Yes, 8MP"
        }
      ]
    },
    {
      "name": "Dimensions",
      "specifications": [
        {
          "key": "Size",
          "value": "67x138.1x6.9mm"
        },
        {
          "key": "Weight",
          "value": "149 gm"
        }
      ]
    }
  ],
  "2001": [
    {
      "name": "General",
      "specifications": [
        {
          "key": "Touch Screen",
          "value": "Yes"
        },
        {
          "key": "SIM Type",
          "value": "GSM, Single Sim"
        },
        {
          "key": "Sim Size",
          "value": "Nano Sim"
        },
        {
          "key": "Video Calling",
          "value": "Yes"
        }
      ]
    },
    {
      "name": "Platform",
      "specifications": [
        {
          "key": "Processor",
          "value": "A7 Chip with M7 Co-processor"
        },
        {
          "key": "OS",
          "value": "iOS 7"
        }
      ]
    },
    {
      "name": "Display",
      "specifications": [
        {
          "key": "Screen Size",
          "value": "9.7 inches"
        },
        {
          "key": "Screen Type",
          "value": "Retina display"
        },
        {
          "key": "Screen Resolution",
          "value": "2048 x 1536 pixels"
        }
      ]
    },
    {
      "name": "Memory & Storage",
      "specifications": [
        {
          "key": "RAM",
          "value": "1GB"
        },
        {
          "key": "Internal Storage",
          "value": "128GB"
        }
      ]
    },
    {
      "name": "Camera",
      "specifications": [
        {
          "key": "Primary Camera",
          "value": "Yes, 5MP"
        },
        {
          "key": "Secondary Camera",
          "value": "Yes, 1.2MP"
        }
      ]
    },
    {
      "name": "Dimensions",
      "specifications": [
        {
          "key": "Size",
          "value": "169.5 x 240 x 7.5 mm"
        },
        {
          "key": "Weight",
          "value": "478 gm"
        }
      ]
    }
  ],
  "2002": [
    {
      "name": "General",
      "specifications": [
        {
          "key": "Touch Screen",
          "value": "Yes"
        },
        {
          "key": "SIM Type",
          "value": "No sim"
        },
        {
          "key": "Video Calling",
          "value": "Yes"
        }
      ]
    },
    {
      "name": "Platform",
      "specifications": [
        {
          "key": "Processor",
          "value": "2.2 GHz NVIDIA Tegra K1 ARM Cortex-A15 Quad Core"
        },
        {
          "key": "OS",
          "value": "Android 4.4.4 (KitKat)"
        }
      ]
    },
    {
      "name": "Display",
      "specifications": [
        {
          "key": "Screen Size",
          "value": "7.9 inches"
        },
        {
          "key": "Screen Type",
          "value": "FullHD"
        },
        {
          "key": "Screen Resolution",
          "value": "2048 x 1536 pixels"
        }
      ]
    },
    {
      "name": "Memory & Storage",
      "specifications": [
        {
          "key": "RAM",
          "value": "2GB"
        },
        {
          "key": "Internal Storage",
          "value": "16GB"
        },
        {
          "key": "Expandable Storage",
          "value": "128GB"
        }
      ]
    },
    {
      "name": "Camera",
      "specifications": [
        {
          "key": "Primary Camera",
          "value": "Yes, 8MP"
        },
        {
          "key": "Secondary Camera",
          "value": "Yes, 5MP"
        }
      ]
    },
    {
      "name": "Dimensions",
      "specifications": [
        {
          "key": "Size",
          "value": "67x138.1x6.9mm"
        },
        {
          "key": "Weight",
          "value": "360 gm"
        }
      ]
    }
  ],
  "2003": [
    {
      "name": "General",
      "specifications": [
        {
          "key": "Touch Screen",
          "value": "Yes"
        },
        {
          "key": "SIM Type",
          "value": "No Sim"
        },
        {
          "key": "Video Calling",
          "value": "Yes"
        }
      ]
    },
    {
      "name": "Platform",
      "specifications": [
        {
          "key": "Processor",
          "value": "1.4 GHz Snapdragon processor"
        },
        {
          "key": "OS",
          "value": "Android 5.0 (Lollipop)"
        }
      ]
    },
    {
      "name": "Display",
      "specifications": [
        {
          "key": "Screen Size",
          "value": "7 inches"
        },
        {
          "key": "Screen Type",
          "value": "IPS display"
        },
        {
          "key": "Screen Resolution",
          "value": "1280 x 800 pixels"
        }
      ]
    },
    {
      "name": "Memory & Storage",
      "specifications": [
        {
          "key": "RAM",
          "value": "1GB"
        },
        {
          "key": "Internal Storage",
          "value": "16GB"
        }
      ]
    },
    {
      "name": "Camera",
      "specifications": [
        {
          "key": "Primary Camera",
          "value": "Yes, 5MP"
        },
        {
          "key": "Secondary Camera",
          "value": "Yes, 0.3MP"
        }
      ]
    },
    {
      "name": "Dimensions",
      "specifications": [
        {
          "key": "Size",
          "value": "120 x 190 x 9.4 mm"
        },
        {
          "key": "Weight",
          "value": "320 gm"
        }
      ]
    }
  ],
  "2004": [
    {
      "name": "General",
      "specifications": [
        {
          "key": "Touch Screen",
          "value": "Yes"
        },
        {
          "key": "SIM Type",
          "value": "GSM, Single Sim"
        },
        {
          "key": "Sim Size",
          "value": "Nano Sim"
        },
        {
          "key": "Video Calling",
          "value": "Yes"
        }
      ]
    },
    {
      "name": "Platform",
      "specifications": [
        {
          "key": "Processor",
          "value": "A7 Chip with M7 Co-processor"
        },
        {
          "key": "OS",
          "value": "iOS 7"
        }
      ]
    },
    {
      "name": "Display",
      "specifications": [
        {
          "key": "Screen Size",
          "value": "9.7 inches"
        },
        {
          "key": "Screen Type",
          "value": "Retina display"
        },
        {
          "key": "Screen Resolution",
          "value": "2048 x 1536 pixels"
        }
      ]
    },
    {
      "name": "Memory & Storage",
      "specifications": [
        {
          "key": "RAM",
          "value": "1GB"
        },
        {
          "key": "Internal Storage",
          "value": "16GB"
        }
      ]
    },
    {
      "name": "Camera",
      "specifications": [
        {
          "key": "Primary Camera",
          "value": "Yes, 5MP"
        },
        {
          "key": "Secondary Camera",
          "value": "Yes, 1.2MP"
        }
      ]
    },
    {
      "name": "Dimensions",
      "specifications": [
        {
          "key": "Size",
          "value": "169.5 x 240 x 7.5 mm"
        },
        {
          "key": "Weight",
          "value": "331 gm"
        }
      ]
    }
  ],
  "2005": [
    {
      "name": "General",
      "specifications": [
        {
          "key": "Touch Screen",
          "value": "Yes"
        },
        {
          "key": "SIM Type",
          "value": "No Sim"
        },
        {
          "key": "Video Calling",
          "value": "Yes"
        }
      ]
    },
    {
      "name": "Platform",
      "specifications": [
        {
          "key": "Processor",
          "value": "1.33 GHz Intel Atom Z3530 Quad Core Processor"
        },
        {
          "key": "OS",
          "value": "Android v4.4 (KitKat) OS"
        }
      ]
    },
    {
      "name": "Display",
      "specifications": [
        {
          "key": "Screen Size",
          "value": "8 inches"
        },
        {
          "key": "Screen Type",
          "value": "IPS display"
        },
        {
          "key": "Screen Resolution",
          "value": "1280 x 800 pixels"
        }
      ]
    },
    {
      "name": "Memory & Storage",
      "specifications": [
        {
          "key": "RAM",
          "value": "2GB"
        },
        {
          "key": "Internal Storage",
          "value": "16GB"
        }
      ]
    },
    {
      "name": "Camera",
      "specifications": [
        {
          "key": "Primary Camera",
          "value": "Yes, 5MP"
        },
        {
          "key": "Secondary Camera",
          "value": "Yes, 2MP"
        }
      ]
    },
    {
      "name": "Dimensions",
      "specifications": [
        {
          "key": "Size",
          "value": "67x138.1x6.9mm"
        },
        {
          "key": "Weight",
          "value": "400 gm"
        }
      ]
    }
  ],
  "2006": [
    {
      "name": "General",
      "specifications": [
        {
          "key": "Touch Screen",
          "value": "Yes"
        },
        {
          "key": "SIM Type",
          "value": "No Sim"
        },
        {
          "key": "Video Calling",
          "value": "Yes"
        }
      ]
    },
    {
      "name": "Platform",
      "specifications": [
        {
          "key": "Processor",
          "value": "Intel Clover Trail Z2520 Processor"
        },
        {
          "key": "OS",
          "value": "Android v4.4 (KitKat) OS"
        }
      ]
    },
    {
      "name": "Display",
      "specifications": [
        {
          "key": "Screen Size",
          "value": "7 inches"
        },
        {
          "key": "Screen Type",
          "value": "IPS display"
        },
        {
          "key": "Screen Resolution",
          "value": "1280 x 800 pixels"
        }
      ]
    },
    {
      "name": "Memory & Storage",
      "specifications": [
        {
          "key": "RAM",
          "value": "1GB"
        },
        {
          "key": "Internal Storage",
          "value": "16GB"
        }
      ]
    },
    {
      "name": "Camera",
      "specifications": [
        {
          "key": "Primary Camera",
          "value": "Yes, 2MP"
        },
        {
          "key": "Secondary Camera",
          "value": "Yes, 0.2MP"
        }
      ]
    },
    {
      "name": "Dimensions",
      "specifications": [
        {
          "key": "Size",
          "value": "192 x 10.7 x 110 mm"
        },
        {
          "key": "Weight",
          "value": "290 gm"
        }
      ]
    }
  ],
  "2007": [
    {
      "name": "General",
      "specifications": [
        {
          "key": "Call Features",
          "value": "Loudspeaker"
        },
        {
          "key": "Touch Screen",
          "value": "Yes"
        },
        {
          "key": "SIM Type",
          "value": "GSM, Single Sim"
        },
        {
          "key": "Sim Size",
          "value": "Normal Sim"
        },
        {
          "key": "Video Calling",
          "value": "Yes"
        }
      ]
    },
    {
      "name": "Platform",
      "specifications": [
        {
          "key": "Processor",
          "value": "1.3 GHz Quad Core Processor"
        },
        {
          "key": "OS",
          "value": "Android v4.4 (KitKat) OS"
        }
      ]
    },
    {
      "name": "Display",
      "specifications": [
        {
          "key": "Screen Size",
          "value": "9.6 inches"
        },
        {
          "key": "Screen Type",
          "value": "WXGA display"
        },
        {
          "key": "Screen Resolution",
          "value": "1280 x 800 pixels"
        }
      ]
    },
    {
      "name": "Memory & Storage",
      "specifications": [
        {
          "key": "RAM",
          "value": "1.5GB"
        },
        {
          "key": "Internal Storage",
          "value": "8GB"
        }
      ]
    },
    {
      "name": "Camera",
      "specifications": [
        {
          "key": "Primary Camera",
          "value": "Yes, 5MP"
        },
        {
          "key": "Secondary Camera",
          "value": "Yes, 2MP"
        }
      ]
    },
    {
      "name": "Dimensions",
      "specifications": [
        {
          "key": "Size",
          "value": "67x138.1x6.9mm"
        },
        {
          "key": "Weight",
          "value": "300 gm"
        }
      ]
    }
  ],
  "2008": [
    {
      "name": "General",
      "specifications": [
        {
          "key": "Call Features",
          "value": "Loudspeaker"
        },
        {
          "key": "Touch Screen",
          "value": "Yes"
        },
        {
          "key": "SIM Type",
          "value": "GSM, Single Sim"
        },
        {
          "key": "Sim Size",
          "value": "Nano Sim"
        },
        {
          "key": "Video Calling",
          "value": "Yes"
        }
      ]
    },
    {
      "name": "Platform",
      "specifications": [
        {
          "key": "Processor",
          "value": "1.9 GHz Quad Core Processor"
        },
        {
          "key": "OS",
          "value": "Android v4.4 (KitKat) OS"
        }
      ]
    },
    {
      "name": "Display",
      "specifications": [
        {
          "key": "Screen Size",
          "value": "10.5 inches"
        },
        {
          "key": "Screen Type",
          "value": "AMOLED"
        },
        {
          "key": "Screen Resolution",
          "value": "2560x1600 pixels"
        }
      ]
    },
    {
      "name": "Memory & Storage",
      "specifications": [
        {
          "key": "RAM",
          "value": "3GB"
        },
        {
          "key": "Internal Storage",
          "value": "16GB"
        }
      ]
    },
    {
      "name": "Camera",
      "specifications": [
        {
          "key": "Primary Camera",
          "value": "Yes, 8MP"
        },
        {
          "key": "Secondary Camera",
          "value": "Yes, 2MP"
        }
      ]
    },
    {
      "name": "Dimensions",
      "specifications": [
        {
          "key": "Size",
          "value": "67x138.1x6.9mm"
        },
        {
          "key": "Weight",
          "value": "129 gm"
        }
      ]
    }
  ],
  "2009": [
    {
      "name": "General",
      "specifications": [
        {
          "key": "Touch Screen",
          "value": "Yes"
        },
        {
          "key": "SIM Type",
          "value": "No Sim"
        },
        {
          "key": "Video Calling",
          "value": "Yes"
        }
      ]
    },
    {
      "name": "Platform",
      "specifications": [
        {
          "key": "Processor",
          "value": "A8X Chip with M8 Motion Co-processor"
        },
        {
          "key": "OS",
          "value": "iOS 7"
        }
      ]
    },
    {
      "name": "Display",
      "specifications": [
        {
          "key": "Screen Size",
          "value": "9.7 inches"
        },
        {
          "key": "Screen Type",
          "value": "Retina display"
        },
        {
          "key": "Screen Resolution",
          "value": "2048 x 1536 pixels"
        }
      ]
    },
    {
      "name": "Memory & Storage",
      "specifications": [
        {
          "key": "RAM",
          "value": "1GB"
        },
        {
          "key": "Internal Storage",
          "value": "16GB"
        }
      ]
    },
    {
      "name": "Camera",
      "specifications": [
        {
          "key": "Primary Camera",
          "value": "Yes, 8MP"
        },
        {
          "key": "Secondary Camera",
          "value": "Yes, 1.2MP"
        }
      ]
    },
    {
      "name": "Dimensions",
      "specifications": [
        {
          "key": "Size",
          "value": "67x138.1x6.9mm"
        },
        {
          "key": "Weight",
          "value": "437 gm"
        }
      ]
    }
  ],
  "2012": [
    {
      "name": "General",
      "specifications": [
        {
          "key": "Touch Screen",
          "value": "Yes"
        },
        {
          "key": "SIM Type",
          "value": "No Sim"
        },
        {
          "key": "Video Calling",
          "value": "Yes"
        }
      ]
    },
    {
      "name": "Platform",
      "specifications": [
        {
          "key": "Processor",
          "value": "1 GHz Cortex-A8 Dual Core Processor"
        },
        {
          "key": "OS",
          "value": "Android 4.2 (Jelly Bean)"
        }
      ]
    },
    {
      "name": "Display",
      "specifications": [
        {
          "key": "Screen Size",
          "value": "7 inches"
        },
        {
          "key": "Screen Type",
          "value": "Capacitive display"
        },
        {
          "key": "Screen Resolution",
          "value": "2048 x 1536 pixels"
        }
      ]
    },
    {
      "name": "Memory & Storage",
      "specifications": [
        {
          "key": "RAM",
          "value": "512GB"
        },
        {
          "key": "Internal Storage",
          "value": "4GB"
        }
      ]
    },
    {
      "name": "Camera",
      "specifications": [
        {
          "key": "Primary Camera",
          "value": "Yes, 2MP"
        },
        {
          "key": "Secondary Camera",
          "value": "Yes, 0.2MP"
        }
      ]
    },
    {
      "name": "Dimensions",
      "specifications": [
        {
          "key": "Size",
          "value": "67x138.1x6.9mm"
        },
        {
          "key": "Weight",
          "value": "437 gm"
        }
      ]
    }
  ],
  "2013": [
    {
      "name": "General",
      "specifications": [
        {
          "key": "Touch Screen",
          "value": "Yes"
        },
        {
          "key": "SIM Type",
          "value": "No Sim"
        },
        {
          "key": "Video Calling",
          "value": "Yes"
        }
      ]
    },
    {
      "name": "Platform",
      "specifications": [
        {
          "key": "Processor",
          "value": "1.9 GHz Quad Core Processor"
        },
        {
          "key": "OS",
          "value": "Android 4.2 (Jelly Bean)"
        }
      ]
    },
    {
      "name": "Display",
      "specifications": [
        {
          "key": "Screen Size",
          "value": "7 inches"
        },
        {
          "key": "Screen Type",
          "value": "IPS display"
        },
        {
          "key": "Screen Resolution",
          "value": "2048 x 1536 pixels"
        }
      ]
    },
    {
      "name": "Memory & Storage",
      "specifications": [
        {
          "key": "RAM",
          "value": "1GB"
        },
        {
          "key": "Internal Storage",
          "value": "16GB"
        }
      ]
    },
    {
      "name": "Camera",
      "specifications": [
        {
          "key": "Primary Camera",
          "value": "Yes, 5MP"
        },
        {
          "key": "Secondary Camera",
          "value": "Yes, 1.2MP"
        }
      ]
    },
    {
      "name": "Dimensions",
      "specifications": [
        {
          "key": "Size",
          "value": "67x138.1x6.9mm"
        },
        {
          "key": "Weight",
          "value": "437 gm"
        }
      ]
    }
  ],
  "2015": [
    {
      "name": "General",
      "specifications": [
        {
          "key": "Touch Screen",
          "value": "Yes"
        },
        {
          "key": "SIM Type",
          "value": "No Sim"
        },
        {
          "key": "Video Calling",
          "value": "Yes"
        }
      ]
    },
    {
      "name": "Platform",
      "specifications": [
        {
          "key": "Processor",
          "value": "2 GHz Intel Atom Z2580 Dual Core Processor"
        },
        {
          "key": "OS",
          "value": "Android v4.2 (Jelly Bean) OS"
        }
      ]
    },
    {
      "name": "Display",
      "specifications": [
        {
          "key": "Screen Size",
          "value": "8 inches"
        },
        {
          "key": "Screen Type",
          "value": "IPS display"
        },
        {
          "key": "Screen Resolution",
          "value": "1280 x 800 pixels"
        }
      ]
    },
    {
      "name": "Memory & Storage",
      "specifications": [
        {
          "key": "RAM",
          "value": "2GB"
        },
        {
          "key": "Internal Storage",
          "value": "16GB"
        }
      ]
    },
    {
      "name": "Camera",
      "specifications": [
        {
          "key": "Primary Camera",
          "value": "Yes, 5MP"
        },
        {
          "key": "Secondary Camera",
          "value": "Yes, 2MP"
        }
      ]
    },
    {
      "name": "Dimensions",
      "specifications": [
        {
          "key": "Size",
          "value": "67x138.1x6.9mm"
        },
        {
          "key": "Weight",
          "value": "350 gm"
        }
      ]
    }
  ],
  "3001": [
    {
      "name": "General",
      "specifications": [
        {
          "key": "Touch Screen",
          "value": "No"
        },
        {
          "key": "Model ID",
          "value": "ME294HN/A"
        },
        {
          "key": "Model ID",
          "value": "Macbook Pro"
        }
      ]
    },
    {
      "name": "Communication",
      "specifications": [
        {
          "key": "Bluetooth",
          "value": "v4.0"
        },
        {
          "key": "Wireless LAN",
          "value": "IEEE 802.11a/b/g/n"
        }
      ]
    },
    {
      "name": "Display",
      "specifications": [
        {
          "key": "Screen Size",
          "value": "15.25 inches"
        },
        {
          "key": "Resolution",
          "value": "2880 x 1800 pixels"
        }
      ]
    },
    {
      "name": "Memory & Storage",
      "specifications": [
        {
          "key": "RAM",
          "value": "16GB"
        },
        {
          "key": "HDD Capacity",
          "value": "512GB"
        }
      ]
    },
    {
      "name": "Graphics",
      "specifications": [
        {
          "key": "Graphic Processor",
          "value": "Intel Iris Pro Graphics NVIDIA GE Force GT750M"
        },
        {
          "key": "Dedicated Graphics Memory Capacity",
          "value": "2GB"
        }
      ]
    },
    {
      "name": "Processor",
      "specifications": [
        {
          "key": "Brand",
          "value": "Intel"
        },
        {
          "key": "Processor",
          "value": "Core i7"
        }
      ]
    }
  ],
  "3002": [
    {
      "name": "General",
      "specifications": [
        {
          "key": "Touch Screen",
          "value": "No"
        },
        {
          "key": "Model ID",
          "value": "ME294HN/A"
        },
        {
          "key": "Model ID",
          "value": "Macbook Pro"
        }
      ]
    },
    {
      "name": "Communication",
      "specifications": [
        {
          "key": "Bluetooth",
          "value": "v4.0"
        },
        {
          "key": "Wireless LAN",
          "value": "IEEE 802.11a/b/g/n"
        }
      ]
    },
    {
      "name": "Display",
      "specifications": [
        {
          "key": "Screen Size",
          "value": "15.25 inches"
        },
        {
          "key": "Resolution",
          "value": "2880 x 1800 pixels"
        }
      ]
    },
    {
      "name": "Memory & Storage",
      "specifications": [
        {
          "key": "RAM",
          "value": "16GB"
        },
        {
          "key": "HDD Capacity",
          "value": "512GB"
        }
      ]
    },
    {
      "name": "Graphics",
      "specifications": [
        {
          "key": "Graphic Processor",
          "value": "Intel Iris Pro Graphics NVIDIA GE Force GT750M"
        },
        {
          "key": "Dedicated Graphics Memory Capacity",
          "value": "2GB"
        }
      ]
    },
    {
      "name": "Processor",
      "specifications": [
        {
          "key": "Brand",
          "value": "Intel"
        },
        {
          "key": "Processor",
          "value": "Core i7"
        }
      ]
    }
  ],
  "3003": [
    {
      "name": "General",
      "specifications": [
        {
          "key": "Touch Screen",
          "value": "No"
        },
        {
          "key": "Model ID",
          "value": "ME294HN/A"
        },
        {
          "key": "Model ID",
          "value": "Macbook Pro"
        }
      ]
    },
    {
      "name": "Communication",
      "specifications": [
        {
          "key": "Bluetooth",
          "value": "v4.0"
        },
        {
          "key": "Wireless LAN",
          "value": "IEEE 802.11a/b/g/n"
        }
      ]
    },
    {
      "name": "Display",
      "specifications": [
        {
          "key": "Screen Size",
          "value": "15.25 inches"
        },
        {
          "key": "Resolution",
          "value": "2880 x 1800 pixels"
        }
      ]
    },
    {
      "name": "Memory & Storage",
      "specifications": [
        {
          "key": "RAM",
          "value": "16GB"
        },
        {
          "key": "HDD Capacity",
          "value": "512GB"
        }
      ]
    },
    {
      "name": "Graphics",
      "specifications": [
        {
          "key": "Graphic Processor",
          "value": "Intel Iris Pro Graphics NVIDIA GE Force GT750M"
        },
        {
          "key": "Dedicated Graphics Memory Capacity",
          "value": "2GB"
        }
      ]
    },
    {
      "name": "Processor",
      "specifications": [
        {
          "key": "Brand",
          "value": "Intel"
        },
        {
          "key": "Processor",
          "value": "Core i7"
        }
      ]
    }
  ],
  "3004": [
    {
      "name": "General",
      "specifications": [
        {
          "key": "Touch Screen",
          "value": "No"
        },
        {
          "key": "Model ID",
          "value": "ME294HN/A"
        },
        {
          "key": "Model ID",
          "value": "Macbook Pro"
        }
      ]
    },
    {
      "name": "Communication",
      "specifications": [
        {
          "key": "Bluetooth",
          "value": "v4.0"
        },
        {
          "key": "Wireless LAN",
          "value": "IEEE 802.11a/b/g/n"
        }
      ]
    },
    {
      "name": "Display",
      "specifications": [
        {
          "key": "Screen Size",
          "value": "15.25 inches"
        },
        {
          "key": "Resolution",
          "value": "2880 x 1800 pixels"
        }
      ]
    },
    {
      "name": "Memory & Storage",
      "specifications": [
        {
          "key": "RAM",
          "value": "16GB"
        },
        {
          "key": "HDD Capacity",
          "value": "512GB"
        }
      ]
    },
    {
      "name": "Graphics",
      "specifications": [
        {
          "key": "Graphic Processor",
          "value": "Intel Iris Pro Graphics NVIDIA GE Force GT750M"
        },
        {
          "key": "Dedicated Graphics Memory Capacity",
          "value": "2GB"
        }
      ]
    },
    {
      "name": "Processor",
      "specifications": [
        {
          "key": "Brand",
          "value": "Intel"
        },
        {
          "key": "Processor",
          "value": "Core i7"
        }
      ]
    }
  ],
  "3005": [
    {
      "name": "General",
      "specifications": [
        {
          "key": "Touch Screen",
          "value": "No"
        },
        {
          "key": "Model ID",
          "value": "ME294HN/A"
        },
        {
          "key": "Model ID",
          "value": "Macbook Pro"
        }
      ]
    },
    {
      "name": "Communication",
      "specifications": [
        {
          "key": "Bluetooth",
          "value": "v4.0"
        },
        {
          "key": "Wireless LAN",
          "value": "IEEE 802.11a/b/g/n"
        }
      ]
    },
    {
      "name": "Display",
      "specifications": [
        {
          "key": "Screen Size",
          "value": "15.25 inches"
        },
        {
          "key": "Resolution",
          "value": "2880 x 1800 pixels"
        }
      ]
    },
    {
      "name": "Memory & Storage",
      "specifications": [
        {
          "key": "RAM",
          "value": "16GB"
        },
        {
          "key": "HDD Capacity",
          "value": "512GB"
        }
      ]
    },
    {
      "name": "Graphics",
      "specifications": [
        {
          "key": "Graphic Processor",
          "value": "Intel Iris Pro Graphics NVIDIA GE Force GT750M"
        },
        {
          "key": "Dedicated Graphics Memory Capacity",
          "value": "2GB"
        }
      ]
    },
    {
      "name": "Processor",
      "specifications": [
        {
          "key": "Brand",
          "value": "Intel"
        },
        {
          "key": "Processor",
          "value": "Core i7"
        }
      ]
    }
  ],
  "3006": [
    {
      "name": "General",
      "specifications": [
        {
          "key": "Touch Screen",
          "value": "No"
        },
        {
          "key": "Model ID",
          "value": "ME294HN/A"
        },
        {
          "key": "Model ID",
          "value": "Macbook Pro"
        }
      ]
    },
    {
      "name": "Communication",
      "specifications": [
        {
          "key": "Bluetooth",
          "value": "v4.0"
        },
        {
          "key": "Wireless LAN",
          "value": "IEEE 802.11a/b/g/n"
        }
      ]
    },
    {
      "name": "Display",
      "specifications": [
        {
          "key": "Screen Size",
          "value": "15.25 inches"
        },
        {
          "key": "Resolution",
          "value": "2880 x 1800 pixels"
        }
      ]
    },
    {
      "name": "Memory & Storage",
      "specifications": [
        {
          "key": "RAM",
          "value": "16GB"
        },
        {
          "key": "HDD Capacity",
          "value": "512GB"
        }
      ]
    },
    {
      "name": "Graphics",
      "specifications": [
        {
          "key": "Graphic Processor",
          "value": "Intel Iris Pro Graphics NVIDIA GE Force GT750M"
        },
        {
          "key": "Dedicated Graphics Memory Capacity",
          "value": "2GB"
        }
      ]
    },
    {
      "name": "Processor",
      "specifications": [
        {
          "key": "Brand",
          "value": "Intel"
        },
        {
          "key": "Processor",
          "value": "Core i7"
        }
      ]
    }
  ],
  "3007": [
    {
      "name": "General",
      "specifications": [
        {
          "key": "Touch Screen",
          "value": "No"
        },
        {
          "key": "Model ID",
          "value": "ME294HN/A"
        },
        {
          "key": "Model ID",
          "value": "Macbook Pro"
        }
      ]
    },
    {
      "name": "Communication",
      "specifications": [
        {
          "key": "Bluetooth",
          "value": "v4.0"
        },
        {
          "key": "Wireless LAN",
          "value": "IEEE 802.11a/b/g/n"
        }
      ]
    },
    {
      "name": "Display",
      "specifications": [
        {
          "key": "Screen Size",
          "value": "15.25 inches"
        },
        {
          "key": "Resolution",
          "value": "2880 x 1800 pixels"
        }
      ]
    },
    {
      "name": "Memory & Storage",
      "specifications": [
        {
          "key": "RAM",
          "value": "16GB"
        },
        {
          "key": "HDD Capacity",
          "value": "512GB"
        }
      ]
    },
    {
      "name": "Graphics",
      "specifications": [
        {
          "key": "Graphic Processor",
          "value": "Intel Iris Pro Graphics NVIDIA GE Force GT750M"
        },
        {
          "key": "Dedicated Graphics Memory Capacity",
          "value": "2GB"
        }
      ]
    },
    {
      "name": "Processor",
      "specifications": [
        {
          "key": "Brand",
          "value": "Intel"
        },
        {
          "key": "Processor",
          "value": "Core i7"
        }
      ]
    }
  ],
  "3008": [
    {
      "name": "General",
      "specifications": [
        {
          "key": "Touch Screen",
          "value": "No"
        },
        {
          "key": "Model ID",
          "value": "ME294HN/A"
        },
        {
          "key": "Model ID",
          "value": "Macbook Pro"
        }
      ]
    },
    {
      "name": "Communication",
      "specifications": [
        {
          "key": "Bluetooth",
          "value": "v4.0"
        },
        {
          "key": "Wireless LAN",
          "value": "IEEE 802.11a/b/g/n"
        }
      ]
    },
    {
      "name": "Display",
      "specifications": [
        {
          "key": "Screen Size",
          "value": "15.25 inches"
        },
        {
          "key": "Resolution",
          "value": "2880 x 1800 pixels"
        }
      ]
    },
    {
      "name": "Memory & Storage",
      "specifications": [
        {
          "key": "RAM",
          "value": "16GB"
        },
        {
          "key": "HDD Capacity",
          "value": "512GB"
        }
      ]
    },
    {
      "name": "Graphics",
      "specifications": [
        {
          "key": "Graphic Processor",
          "value": "Intel Iris Pro Graphics NVIDIA GE Force GT750M"
        },
        {
          "key": "Dedicated Graphics Memory Capacity",
          "value": "2GB"
        }
      ]
    },
    {
      "name": "Processor",
      "specifications": [
        {
          "key": "Brand",
          "value": "Intel"
        },
        {
          "key": "Processor",
          "value": "Core i7"
        }
      ]
    }
  ]
}